{
  "metadata": {
    "date": "2020-03-24T03:56:58.999274857-05:00",
    "FinderVersion": "v0.9.1-6-g3d81f20",
    "language": "eng",
    "language_detected": "",
    "detect_language": false,
    "total_words": 182,
    "total_candidates": 52,
    "total_names": 7
  },
  "names": [
    {
      "type": "Binomial",
      "verbatim": "Rana scapularis.",
      "name": "Rana scapularis",
      "odds": 4404141008.800273,
      "odds_details": {
        "Name": {
          "spLen": {
            "10": 13.127639159348814
          },
          "spDict": {
            "WhiteSpecies": 5628.6125203841275
          },
          "spEnd3": {
            "ris": 335.3641964123935
          },
          "PriorOdds": {
            "true": 0.1
          },
          "uniLen": {
            "4": 0.06813979490435608
          },
          "uniDict": {
            "WhiteGenus": 20194.430603370172
          },
          "abbr": {
            "false": 0.8679430877999654
          },
          "uniEnd3": {
            "ana": 1.488102525428128
          }
        }
      },
      "start": 35,
      "end": 51,
      "annotation": "",
      "verification": {
        "BestResult": {
          "dataSourceId": 3,
          "dataSourceTitle": "ITIS",
          "taxonId": "1101417",
          "matchedName": "Rana scapularis Harlan, 1826",
          "matchedCanonical": "Rana scapularis",
          "currentName": "Lithobates catesbeianus (Shaw, 1802)",
          "isSynonym": true,
          "classificationPath": "Animalia|Bilateria|Deuterostomia|Chordata|Vertebrata|Gnathostomata|Tetrapoda|Amphibia|Anura|Ranidae|Lithobates|Lithobates catesbeianus",
          "classificationRank": "Kingdom|Subkingdom|Infrakingdom|Phylum|Subphylum|Infraphylum|Superclass|Class|Order|Family|Genus|Species",
          "classificationIDs": "202423|914154|914156|158852|331030|914179|914181|173420|173423|1094181|773285|775084",
          "matchType": "ExactCanonicalMatch"
        },
        "dataSourcesNum": 2,
        "dataSourceQuality": "HasCuratedSources",
        "retries": 1
      }
    },
    {
      "type": "Binomial",
      "verbatim": "Rana scapularis,",
      "name": "Rana scapularis",
      "odds": 4404141008.800273,
      "odds_details": {
        "Name": {
          "uniLen": {
            "4": 0.06813979490435608
          },
          "uniDict": {
            "WhiteGenus": 20194.430603370172
          },
          "abbr": {
            "false": 0.8679430877999654
          },
          "uniEnd3": {
            "ana": 1.488102525428128
          },
          "spLen": {
            "10": 13.127639159348814
          },
          "spDict": {
            "WhiteSpecies": 5628.6125203841275
          },
          "spEnd3": {
            "ris": 335.3641964123935
          },
          "PriorOdds": {
            "true": 0.1
          }
        }
      },
      "start": 56,
      "end": 72,
      "annotation": "",
      "verification": {
        "BestResult": {
          "dataSourceId": 3,
          "dataSourceTitle": "ITIS",
          "taxonId": "1101417",
          "matchedName": "Rana scapularis Harlan, 1826",
          "matchedCanonical": "Rana scapularis",
          "currentName": "Lithobates catesbeianus (Shaw, 1802)",
          "isSynonym": true,
          "classificationPath": "Animalia|Bilateria|Deuterostomia|Chordata|Vertebrata|Gnathostomata|Tetrapoda|Amphibia|Anura|Ranidae|Lithobates|Lithobates catesbeianus",
          "classificationRank": "Kingdom|Subkingdom|Infrakingdom|Phylum|Subphylum|Infraphylum|Superclass|Class|Order|Family|Genus|Species",
          "classificationIDs": "202423|914154|914156|158852|331030|914179|914181|173420|173423|1094181|773285|775084",
          "matchType": "ExactCanonicalMatch"
        },
        "dataSourcesNum": 2,
        "dataSourceQuality": "HasCuratedSources",
        "retries": 1
      }
    },
    {
      "type": "Uninomial",
      "verbatim": "Rana",
      "name": "Rana",
      "odds": 177.7282796257126,
      "odds_details": {
        "Name": {
          "PriorOdds": {
            "true": 0.1
          },
          "uniLen": {
            "4": 0.06813979490435608
          },
          "uniDict": {
            "WhiteGenus": 20194.430603370172
          },
          "abbr": {
            "false": 0.8679430877999654
          },
          "uniEnd3": {
            "ana": 1.488102525428128
          }
        }
      },
      "start": 348,
      "end": 352,
      "annotation": "",
      "verification": {
        "BestResult": {
          "dataSourceId": 1,
          "dataSourceTitle": "Catalogue of Life",
          "taxonId": "55006463",
          "matchedName": "Rana",
          "matchedCanonical": "Rana",
          "currentName": "Rana",
          "classificationPath": "Animalia|Chordata|Amphibia|Anura|Ranidae|Rana",
          "classificationRank": "kingdom|phylum|class|order|family|genus",
          "classificationIDs": "54767744|54767745|54771347|54771357|54771364|55006463",
          "matchType": "ExactMatch"
        },
        "dataSourcesNum": 22,
        "dataSourceQuality": "HasCuratedSources",
        "retries": 1
      }
    },
    {
      "type": "Binomial",
      "verbatim": "Rana fontinalis",
      "name": "Rana fontinalis",
      "odds": 5094342211.671958,
      "odds_details": {
        "Name": {
          "abbr": {
            "false": 0.8679430877999654
          },
          "uniEnd3": {
            "ana": 1.488102525428128
          },
          "spEnd3": {
            "lis": 387.92127196955965
          },
          "spLen": {
            "10": 13.127639159348814
          },
          "spDict": {
            "WhiteSpecies": 5628.6125203841275
          },
          "PriorOdds": {
            "true": 0.1
          },
          "uniLen": {
            "4": 0.06813979490435608
          },
          "uniDict": {
            "WhiteGenus": 20194.430603370172
          }
        }
      },
      "start": 445,
      "end": 460,
      "annotation": "",
      "verification": {
        "BestResult": {
          "dataSourceId": 3,
          "dataSourceTitle": "ITIS",
          "taxonId": "1101690",
          "matchedName": "Rana fontinalis LeConte, 1825",
          "matchedCanonical": "Rana fontinalis",
          "currentName": "Lithobates clamitans (Latreille in Sonnini de Manoncourt and Latreille, 1801)",
          "isSynonym": true,
          "classificationPath": "Animalia|Bilateria|Deuterostomia|Chordata|Vertebrata|Gnathostomata|Tetrapoda|Amphibia|Anura|Ranidae|Lithobates|Lithobates clamitans",
          "classificationRank": "Kingdom|Subkingdom|Infrakingdom|Phylum|Subphylum|Infraphylum|Superclass|Class|Order|Family|Genus|Species",
          "classificationIDs": "202423|914154|914156|158852|331030|914179|914181|173420|173423|1094181|773285|775087",
          "matchType": "ExactCanonicalMatch"
        },
        "dataSourcesNum": 1,
        "dataSourceQuality": "HasCuratedSources",
        "retries": 1
      }
    },
    {
      "type": "Binomial",
      "verbatim": "Rana sylvatica.",
      "name": "Rana sylvatica",
      "odds": 5224821091.9834795,
      "odds_details": {
        "Name": {
          "abbr": {
            "false": 0.8679430877999654
          },
          "uniEnd3": {
            "ana": 1.488102525428128
          },
          "spLen": {
            "9": 10.081642477424332
          },
          "spDict": {
            "WhiteSpecies": 5628.6125203841275
          },
          "spEnd3": {
            "ica": 518.0626019206378
          },
          "PriorOdds": {
            "true": 0.1
          },
          "uniLen": {
            "4": 0.06813979490435608
          },
          "uniDict": {
            "WhiteGenus": 20194.430603370172
          }
        }
      },
      "start": 920,
      "end": 935,
      "annotation": "",
      "verification": {
        "BestResult": {
          "dataSourceId": 1,
          "dataSourceTitle": "Catalogue of Life",
          "taxonId": "7162717",
          "matchedName": "Rana sylvatica LeConte, 1825",
          "matchedCanonical": "Rana sylvatica",
          "currentName": "Lithobates sylvaticus (LeConte, 1825)",
          "isSynonym": true,
          "classificationPath": "Animalia|Chordata|Amphibia|Anura|Ranidae|Lithobates|Lithobates sylvaticus",
          "classificationRank": "kingdom|phylum|class|order|family|genus|species",
          "classificationIDs": "54767744|54767745|54771347|54771357|54771364|54923952|7161264",
          "matchType": "ExactCanonicalMatch"
        },
        "dataSourcesNum": 19,
        "dataSourceQuality": "HasCuratedSources",
        "retries": 1
      }
    },
    {
      "type": "Binomial",
      "verbatim": "Rana sylvatica,",
      "name": "Rana sylvatica",
      "odds": 5224821091.9834795,
      "odds_details": {
        "Name": {
          "spDict": {
            "WhiteSpecies": 5628.6125203841275
          },
          "spEnd3": {
            "ica": 518.0626019206378
          },
          "PriorOdds": {
            "true": 0.1
          },
          "uniLen": {
            "4": 0.06813979490435608
          },
          "uniDict": {
            "WhiteGenus": 20194.430603370172
          },
          "abbr": {
            "false": 0.8679430877999654
          },
          "uniEnd3": {
            "ana": 1.488102525428128
          },
          "spLen": {
            "9": 10.081642477424332
          }
        }
      },
      "start": 953,
      "end": 968,
      "annotation": "",
      "verification": {
        "BestResult": {
          "dataSourceId": 1,
          "dataSourceTitle": "Catalogue of Life",
          "taxonId": "7162717",
          "matchedName": "Rana sylvatica LeConte, 1825",
          "matchedCanonical": "Rana sylvatica",
          "currentName": "Lithobates sylvaticus (LeConte, 1825)",
          "isSynonym": true,
          "classificationPath": "Animalia|Chordata|Amphibia|Anura|Ranidae|Lithobates|Lithobates sylvaticus",
          "classificationRank": "kingdom|phylum|class|order|family|genus|species",
          "classificationIDs": "54767744|54767745|54771347|54771357|54771364|54923952|7161264",
          "matchType": "ExactCanonicalMatch"
        },
        "dataSourcesNum": 19,
        "dataSourceQuality": "HasCuratedSources",
        "retries": 1
      }
    },
    {
      "type": "Binomial",
      "verbatim": "Rana pennsylvanica,",
      "name": "Rana pennsylvanica",
      "odds": 11673323958.541264,
      "odds_details": {
        "Name": {
          "PriorOdds": {
            "true": 0.1
          },
          "uniLen": {
            "4": 0.06813979490435608
          },
          "uniDict": {
            "WhiteGenus": 20194.430603370172
          },
          "abbr": {
            "false": 0.8679430877999654
          },
          "uniEnd3": {
            "ana": 1.488102525428128
          },
          "spLen": {
            "13": 22.52446095307121
          },
          "spDict": {
            "WhiteSpecies": 5628.6125203841275
          },
          "spEnd3": {
            "ica": 518.0626019206378
          }
        }
      },
      "start": 1037,
      "end": 1056,
      "annotation": "",
      "verification": {
        "BestResult": {
          "dataSourceId": 3,
          "dataSourceTitle": "ITIS",
          "taxonId": "1101740",
          "matchedName": "Rana pennsylvanica Harlan, 1826",
          "matchedCanonical": "Rana pennsylvanica",
          "currentName": "Lithobates sylvaticus (LeConte, 1825)",
          "isSynonym": true,
          "classificationPath": "Animalia|Bilateria|Deuterostomia|Chordata|Vertebrata|Gnathostomata|Tetrapoda|Amphibia|Anura|Ranidae|Lithobates|Lithobates sylvaticus",
          "classificationRank": "Kingdom|Subkingdom|Infrakingdom|Phylum|Subphylum|Infraphylum|Superclass|Class|Order|Family|Genus|Species",
          "classificationIDs": "202423|914154|914156|158852|331030|914179|914181|173420|173423|1094181|773285|775117",
          "matchType": "ExactCanonicalMatch"
        },
        "dataSourcesNum": 1,
        "dataSourceQuality": "HasCuratedSources",
        "retries": 1
      }
    }
  ]
}
