{
  "metadata": {
    "date": "2020-03-24T03:55:42.392083698-05:00",
    "FinderVersion": "v0.9.1-6-g3d81f20",
    "language": "eng",
    "language_detected": "",
    "detect_language": false,
    "total_words": 267,
    "total_candidates": 26,
    "total_names": 2
  },
  "names": [
    {
      "type": "PossibleBinomial",
      "verbatim": "N. intricata",
      "name": "N. intricata",
      "odds": 40926240.69493145,
      "odds_details": {
        "Name": {
          "abbr": {
            "true": 4.640509995272512
          },
          "spDict": {
            "WhiteSpecies": 5628.6125203841275
          },
          "spEnd3": {
            "ata": 1554.1878057619133
          },
          "spLen": {
            "9": 10.081642477424332
          },
          "PriorOdds": {
            "true": 0.1
          }
        }
      },
      "start": 374,
      "end": 386,
      "annotation": "",
      "verification": {
        "BestResult": {
          "matchType": "NoMatch"
        },
        "retries": 1
      }
    },
    {
      "type": "PossibleBinomial",
      "verbatim": "N. canrena.",
      "name": "N. canrena",
      "odds": 694301.0738319342,
      "odds_details": {
        "Name": {
          "abbr": {
            "true": 4.640509995272512
          },
          "spLen": {
            "7": 4.425451988126818
          },
          "spDict": {
            "WhiteSpecies": 5628.6125203841275
          },
          "spEnd3": {
            "ena": 60.06522920818988
          },
          "PriorOdds": {
            "true": 0.1
          }
        }
      },
      "start": 465,
      "end": 476,
      "annotation": "",
      "verification": {
        "BestResult": {
          "matchType": "NoMatch"
        },
        "retries": 1
      }
    }
  ]
}
