{
  "metadata": {
    "date": "2020-03-24T03:54:18.133646345-05:00",
    "FinderVersion": "v0.9.1-6-g3d81f20",
    "language": "eng",
    "language_detected": "",
    "detect_language": false,
    "total_words": 249,
    "total_candidates": 42,
    "total_names": 9
  },
  "names": [
    {
      "type": "PossibleBinomial",
      "verbatim": "T. bartramia.",
      "name": "T. bartramia",
      "odds": 26332.879812339073,
      "odds_details": {
        "Name": {
          "spDict": {
            "WhiteSpecies": 5628.6125203841275
          },
          "PriorOdds": {
            "true": 0.1
          },
          "abbr": {
            "true": 4.640509995272512
          },
          "spLen": {
            "9": 10.081642477424332
          }
        }
      },
      "start": 221,
      "end": 234,
      "annotation": "",
      "verification": {
        "BestResult": {
          "matchType": "NoMatch"
        },
        "retries": 1
      }
    },
    {
      "type": "Binomial(nlp)",
      "verbatim": "Totanus \r\r\n hartramius,",
      "name": "Totanus hartramius",
      "odds": 29536781.254927326,
      "odds_details": {
        "Name": {
          "spLen": {
            "10": 13.127639159348814
          },
          "spDict": {
            "NotInDictionary": 0.05328981045086555
          },
          "spEnd3": {
            "ius": 192.70927704294255
          },
          "PriorOdds": {
            "true": 0.1
          },
          "uniLen": {
            "7": 0.8324223452545503
          },
          "uniDict": {
            "WhiteGenus": 20194.430603370172
          },
          "abbr": {
            "false": 0.8679430877999654
          },
          "uniEnd3": {
            "nus": 150.1630730204747
          }
        }
      },
      "start": 252,
      "end": 275,
      "annotation": "",
      "verification": {
        "BestResult": {
          "dataSourceId": 172,
          "dataSourceTitle": "The Paleobiology Database",
          "taxonId": "39583",
          "matchedName": "Totanus Moehring 1758",
          "matchedCanonical": "Totanus",
          "currentName": "Totanus Moehring 1758",
          "classificationPath": "Eucarya|Opisthokonta|Metazoa|Eumetazoa|Triploblastica|Nephrozoa|Deuterostomia|Chordata|Vertebrata|Gnathostomata|Osteichthyes|Sarcopterygii|Dipnotetrapodomorpha|Tetrapodomorpha|Tetrapoda|Reptiliomorpha|Anthracosauria|Batrachosauria|Cotylosauria|Amniota|Sauropsida|Reptilia|Eureptilia|Romeriida|Diapsida|Archosauromorpha|Archosauriformes|Crurotarsi|Archosauria|Avemetatarsalia|Ornithodira|Dinosauromorpha|Dinosauriformes|Dinosauria|Saurischia|Theropoda|Neotheropoda|Averostra|Tetanurae|Avetheropoda|Coelurosauria|Maniraptora|Paraves|Aves|Charadriiformes|Limicolae|Scolopacides|Scolopacoidea|Scolopacidae|Totanus",
          "classificationRank": "unranked clade|unranked clade|subkingdom|unranked clade|unranked clade|unranked clade|unranked clade|unranked clade|unranked clade|unranked clade|unranked clade|superclass|subclass|subclass|unranked clade|unranked clade|unranked clade|unranked clade|unranked clade|unranked clade|unranked clade|class|unranked clade|unranked clade|unranked clade|infraclass|unranked clade|unranked clade|unranked clade|informal|unranked clade|unranked clade|unranked clade|unranked clade|unranked clade|unranked clade|unranked clade|unranked clade|unranked clade|unranked clade|suborder|unranked clade|unranked clade|class|order|suborder|infraorder|superfamily|family|genus",
          "classificationIDs": "288516|212579|2|85325|67102|85323|67145|33815|67149|67344|34881|67348|219195|77135|53190|125547|37177|99766|56749|53189|135358|36322|92204|99771|37768|38182|57091|66477|38215|144376|57250|53366|53207|52775|38505|38513|56397|92043|53374|55483|53940|55486|64113|36616|36640|98938|98941|98943|39581|39583",
          "matchType": "ExactPartialMatch"
        },
        "dataSourcesNum": 7,
        "dataSourceQuality": "HasCuratedSources",
        "retries": 1
      }
    },
    {
      "type": "Binomial(nlp)",
      "verbatim": "Totanus barlramius,",
      "name": "Totanus barlramius",
      "odds": 29536781.254927326,
      "odds_details": {
        "Name": {
          "abbr": {
            "false": 0.8679430877999654
          },
          "uniEnd3": {
            "nus": 150.1630730204747
          },
          "spDict": {
            "NotInDictionary": 0.05328981045086555
          },
          "spEnd3": {
            "ius": 192.70927704294255
          },
          "spLen": {
            "10": 13.127639159348814
          },
          "PriorOdds": {
            "true": 0.1
          },
          "uniLen": {
            "7": 0.8324223452545503
          },
          "uniDict": {
            "WhiteGenus": 20194.430603370172
          }
        }
      },
      "start": 808,
      "end": 827,
      "annotation": "",
      "verification": {
        "BestResult": {
          "dataSourceId": 172,
          "dataSourceTitle": "The Paleobiology Database",
          "taxonId": "39583",
          "matchedName": "Totanus Moehring 1758",
          "matchedCanonical": "Totanus",
          "currentName": "Totanus Moehring 1758",
          "classificationPath": "Eucarya|Opisthokonta|Metazoa|Eumetazoa|Triploblastica|Nephrozoa|Deuterostomia|Chordata|Vertebrata|Gnathostomata|Osteichthyes|Sarcopterygii|Dipnotetrapodomorpha|Tetrapodomorpha|Tetrapoda|Reptiliomorpha|Anthracosauria|Batrachosauria|Cotylosauria|Amniota|Sauropsida|Reptilia|Eureptilia|Romeriida|Diapsida|Archosauromorpha|Archosauriformes|Crurotarsi|Archosauria|Avemetatarsalia|Ornithodira|Dinosauromorpha|Dinosauriformes|Dinosauria|Saurischia|Theropoda|Neotheropoda|Averostra|Tetanurae|Avetheropoda|Coelurosauria|Maniraptora|Paraves|Aves|Charadriiformes|Limicolae|Scolopacides|Scolopacoidea|Scolopacidae|Totanus",
          "classificationRank": "unranked clade|unranked clade|subkingdom|unranked clade|unranked clade|unranked clade|unranked clade|unranked clade|unranked clade|unranked clade|unranked clade|superclass|subclass|subclass|unranked clade|unranked clade|unranked clade|unranked clade|unranked clade|unranked clade|unranked clade|class|unranked clade|unranked clade|unranked clade|infraclass|unranked clade|unranked clade|unranked clade|informal|unranked clade|unranked clade|unranked clade|unranked clade|unranked clade|unranked clade|unranked clade|unranked clade|unranked clade|unranked clade|suborder|unranked clade|unranked clade|class|order|suborder|infraorder|superfamily|family|genus",
          "classificationIDs": "288516|212579|2|85325|67102|85323|67145|33815|67149|67344|34881|67348|219195|77135|53190|125547|37177|99766|56749|53189|135358|36322|92204|99771|37768|38182|57091|66477|38215|144376|57250|53366|53207|52775|38505|38513|56397|92043|53374|55483|53940|55486|64113|36616|36640|98938|98941|98943|39581|39583",
          "matchType": "ExactPartialMatch"
        },
        "dataSourcesNum": 7,
        "dataSourceQuality": "HasCuratedSources",
        "retries": 1
      }
    },
    {
      "type": "Binomial",
      "verbatim": "Tringa longicauda,",
      "name": "Tringa longicauda",
      "odds": 40731037761.54586,
      "odds_details": {
        "Name": {
          "uniEnd3": {
            "nga": 42.54620402246783
          },
          "spEnd3": {
            "uda": 17.51902518572205
          },
          "spLen": {
            "10": 13.127639159348814
          },
          "spDict": {
            "WhiteSpecies": 5628.6125203841275
          },
          "PriorOdds": {
            "true": 0.1
          },
          "uniLen": {
            "6": 0.42193337125672775
          },
          "uniDict": {
            "WhiteGenus": 20194.430603370172
          },
          "abbr": {
            "false": 0.8679430877999654
          }
        }
      },
      "start": 840,
      "end": 858,
      "annotation": "",
      "verification": {
        "BestResult": {
          "dataSourceId": 1,
          "dataSourceTitle": "Catalogue of Life",
          "taxonId": "35539874",
          "matchedName": "Tringa longicauda Bechstein, 1812",
          "matchedCanonical": "Tringa longicauda",
          "currentName": "Bartramia longicauda (Bechstein, 1812)",
          "isSynonym": true,
          "classificationPath": "Animalia|Chordata|Aves|Charadriiformes|Scolopacidae|Bartramia|Bartramia longicauda",
          "classificationRank": "kingdom|phylum|class|order|family|genus|species",
          "classificationIDs": "54767744|54767745|54767746|54773289|54773293|54813015|35518544",
          "matchType": "ExactCanonicalMatch"
        },
        "dataSourcesNum": 5,
        "dataSourceQuality": "HasCuratedSources",
        "retries": 1
      }
    },
    {
      "type": "Binomial",
      "verbatim": "Totanus campestris,",
      "name": "Totanus campestris",
      "odds": 5429182203093.341,
      "odds_details": {
        "Name": {
          "PriorOdds": {
            "true": 0.1
          },
          "uniLen": {
            "7": 0.8324223452545503
          },
          "uniDict": {
            "WhiteGenus": 20194.430603370172
          },
          "abbr": {
            "false": 0.8679430877999654
          },
          "uniEnd3": {
            "nus": 150.1630730204747
          },
          "spDict": {
            "WhiteSpecies": 5628.6125203841275
          },
          "spEnd3": {
            "ris": 335.3641964123935
          },
          "spLen": {
            "10": 13.127639159348814
          }
        }
      },
      "start": 873,
      "end": 892,
      "annotation": "",
      "verification": {
        "BestResult": {
          "dataSourceId": 172,
          "dataSourceTitle": "The Paleobiology Database",
          "taxonId": "39583",
          "matchedName": "Totanus Moehring 1758",
          "matchedCanonical": "Totanus",
          "currentName": "Totanus Moehring 1758",
          "classificationPath": "Eucarya|Opisthokonta|Metazoa|Eumetazoa|Triploblastica|Nephrozoa|Deuterostomia|Chordata|Vertebrata|Gnathostomata|Osteichthyes|Sarcopterygii|Dipnotetrapodomorpha|Tetrapodomorpha|Tetrapoda|Reptiliomorpha|Anthracosauria|Batrachosauria|Cotylosauria|Amniota|Sauropsida|Reptilia|Eureptilia|Romeriida|Diapsida|Archosauromorpha|Archosauriformes|Crurotarsi|Archosauria|Avemetatarsalia|Ornithodira|Dinosauromorpha|Dinosauriformes|Dinosauria|Saurischia|Theropoda|Neotheropoda|Averostra|Tetanurae|Avetheropoda|Coelurosauria|Maniraptora|Paraves|Aves|Charadriiformes|Limicolae|Scolopacides|Scolopacoidea|Scolopacidae|Totanus",
          "classificationRank": "unranked clade|unranked clade|subkingdom|unranked clade|unranked clade|unranked clade|unranked clade|unranked clade|unranked clade|unranked clade|unranked clade|superclass|subclass|subclass|unranked clade|unranked clade|unranked clade|unranked clade|unranked clade|unranked clade|unranked clade|class|unranked clade|unranked clade|unranked clade|infraclass|unranked clade|unranked clade|unranked clade|informal|unranked clade|unranked clade|unranked clade|unranked clade|unranked clade|unranked clade|unranked clade|unranked clade|unranked clade|unranked clade|suborder|unranked clade|unranked clade|class|order|suborder|infraorder|superfamily|family|genus",
          "classificationIDs": "288516|212579|2|85325|67102|85323|67145|33815|67149|67344|34881|67348|219195|77135|53190|125547|37177|99766|56749|53189|135358|36322|92204|99771|37768|38182|57091|66477|38215|144376|57250|53366|53207|52775|38505|38513|56397|92043|53374|55483|53940|55486|64113|36616|36640|98938|98941|98943|39581|39583",
          "matchType": "ExactPartialMatch"
        },
        "dataSourcesNum": 7,
        "dataSourceQuality": "HasCuratedSources",
        "retries": 1
      }
    },
    {
      "type": "Binomial(nlp)",
      "verbatim": "Totanus mdanopygius",
      "name": "Totanus mdanopygius",
      "odds": 59985369.74498382,
      "odds_details": {
        "Name": {
          "uniLen": {
            "7": 0.8324223452545503
          },
          "uniDict": {
            "WhiteGenus": 20194.430603370172
          },
          "abbr": {
            "false": 0.8679430877999654
          },
          "uniEnd3": {
            "nus": 150.1630730204747
          },
          "spLen": {
            "11": 26.660531560828144
          },
          "spDict": {
            "NotInDictionary": 0.05328981045086555
          },
          "spEnd3": {
            "ius": 192.70927704294255
          },
          "PriorOdds": {
            "true": 0.1
          }
        }
      },
      "start": 1034,
      "end": 1053,
      "annotation": "",
      "verification": {
        "BestResult": {
          "dataSourceId": 172,
          "dataSourceTitle": "The Paleobiology Database",
          "taxonId": "39583",
          "matchedName": "Totanus Moehring 1758",
          "matchedCanonical": "Totanus",
          "currentName": "Totanus Moehring 1758",
          "classificationPath": "Eucarya|Opisthokonta|Metazoa|Eumetazoa|Triploblastica|Nephrozoa|Deuterostomia|Chordata|Vertebrata|Gnathostomata|Osteichthyes|Sarcopterygii|Dipnotetrapodomorpha|Tetrapodomorpha|Tetrapoda|Reptiliomorpha|Anthracosauria|Batrachosauria|Cotylosauria|Amniota|Sauropsida|Reptilia|Eureptilia|Romeriida|Diapsida|Archosauromorpha|Archosauriformes|Crurotarsi|Archosauria|Avemetatarsalia|Ornithodira|Dinosauromorpha|Dinosauriformes|Dinosauria|Saurischia|Theropoda|Neotheropoda|Averostra|Tetanurae|Avetheropoda|Coelurosauria|Maniraptora|Paraves|Aves|Charadriiformes|Limicolae|Scolopacides|Scolopacoidea|Scolopacidae|Totanus",
          "classificationRank": "unranked clade|unranked clade|subkingdom|unranked clade|unranked clade|unranked clade|unranked clade|unranked clade|unranked clade|unranked clade|unranked clade|superclass|subclass|subclass|unranked clade|unranked clade|unranked clade|unranked clade|unranked clade|unranked clade|unranked clade|class|unranked clade|unranked clade|unranked clade|infraclass|unranked clade|unranked clade|unranked clade|informal|unranked clade|unranked clade|unranked clade|unranked clade|unranked clade|unranked clade|unranked clade|unranked clade|unranked clade|unranked clade|suborder|unranked clade|unranked clade|class|order|suborder|infraorder|superfamily|family|genus",
          "classificationIDs": "288516|212579|2|85325|67102|85323|67145|33815|67149|67344|34881|67348|219195|77135|53190|125547|37177|99766|56749|53189|135358|36322|92204|99771|37768|38182|57091|66477|38215|144376|57250|53366|53207|52775|38505|38513|56397|92043|53374|55483|53940|55486|64113|36616|36640|98938|98941|98943|39581|39583",
          "matchType": "ExactPartialMatch"
        },
        "dataSourcesNum": 7,
        "dataSourceQuality": "HasCuratedSources",
        "retries": 1
      }
    },
    {
      "type": "Uninomial",
      "verbatim": "Totanus",
      "name": "Totanus",
      "odds": 219093.623660603,
      "odds_details": {
        "Name": {
          "uniLen": {
            "7": 0.8324223452545503
          },
          "uniDict": {
            "WhiteGenus": 20194.430603370172
          },
          "abbr": {
            "false": 0.8679430877999654
          },
          "uniEnd3": {
            "nus": 150.1630730204747
          },
          "PriorOdds": {
            "true": 0.1
          }
        }
      },
      "start": 1421,
      "end": 1428,
      "annotation": "",
      "verification": {
        "BestResult": {
          "dataSourceId": 172,
          "dataSourceTitle": "The Paleobiology Database",
          "taxonId": "39583",
          "matchedName": "Totanus Moehring 1758",
          "matchedCanonical": "Totanus",
          "currentName": "Totanus Moehring 1758",
          "classificationPath": "Eucarya|Opisthokonta|Metazoa|Eumetazoa|Triploblastica|Nephrozoa|Deuterostomia|Chordata|Vertebrata|Gnathostomata|Osteichthyes|Sarcopterygii|Dipnotetrapodomorpha|Tetrapodomorpha|Tetrapoda|Reptiliomorpha|Anthracosauria|Batrachosauria|Cotylosauria|Amniota|Sauropsida|Reptilia|Eureptilia|Romeriida|Diapsida|Archosauromorpha|Archosauriformes|Crurotarsi|Archosauria|Avemetatarsalia|Ornithodira|Dinosauromorpha|Dinosauriformes|Dinosauria|Saurischia|Theropoda|Neotheropoda|Averostra|Tetanurae|Avetheropoda|Coelurosauria|Maniraptora|Paraves|Aves|Charadriiformes|Limicolae|Scolopacides|Scolopacoidea|Scolopacidae|Totanus",
          "classificationRank": "unranked clade|unranked clade|subkingdom|unranked clade|unranked clade|unranked clade|unranked clade|unranked clade|unranked clade|unranked clade|unranked clade|superclass|subclass|subclass|unranked clade|unranked clade|unranked clade|unranked clade|unranked clade|unranked clade|unranked clade|class|unranked clade|unranked clade|unranked clade|infraclass|unranked clade|unranked clade|unranked clade|informal|unranked clade|unranked clade|unranked clade|unranked clade|unranked clade|unranked clade|unranked clade|unranked clade|unranked clade|unranked clade|suborder|unranked clade|unranked clade|class|order|suborder|infraorder|superfamily|family|genus",
          "classificationIDs": "288516|212579|2|85325|67102|85323|67145|33815|67149|67344|34881|67348|219195|77135|53190|125547|37177|99766|56749|53189|135358|36322|92204|99771|37768|38182|57091|66477|38215|144376|57250|53366|53207|52775|38505|38513|56397|92043|53374|55483|53940|55486|64113|36616|36640|98938|98941|98943|39581|39583",
          "matchType": "ExactCanonicalMatch"
        },
        "dataSourcesNum": 7,
        "dataSourceQuality": "HasCuratedSources",
        "retries": 1
      }
    },
    {
      "type": "PossibleBinomial",
      "verbatim": "T. longicauda,",
      "name": "T. longicauda",
      "odds": 600708.2998496903,
      "odds_details": {
        "Name": {
          "spLen": {
            "10": 13.127639159348814
          },
          "spDict": {
            "WhiteSpecies": 5628.6125203841275
          },
          "spEnd3": {
            "uda": 17.51902518572205
          },
          "PriorOdds": {
            "true": 0.1
          },
          "abbr": {
            "true": 4.640509995272512
          }
        }
      },
      "start": 1451,
      "end": 1465,
      "annotation": "",
      "verification": {
        "BestResult": {
          "matchType": "NoMatch"
        },
        "retries": 1
      }
    },
    {
      "type": "Uninomial",
      "verbatim": "Totanus",
      "name": "Totanus",
      "odds": 219093.623660603,
      "odds_details": {
        "Name": {
          "PriorOdds": {
            "true": 0.1
          },
          "uniLen": {
            "7": 0.8324223452545503
          },
          "uniDict": {
            "WhiteGenus": 20194.430603370172
          },
          "abbr": {
            "false": 0.8679430877999654
          },
          "uniEnd3": {
            "nus": 150.1630730204747
          }
        }
      },
      "start": 1562,
      "end": 1569,
      "annotation": "",
      "verification": {
        "BestResult": {
          "dataSourceId": 172,
          "dataSourceTitle": "The Paleobiology Database",
          "taxonId": "39583",
          "matchedName": "Totanus Moehring 1758",
          "matchedCanonical": "Totanus",
          "currentName": "Totanus Moehring 1758",
          "classificationPath": "Eucarya|Opisthokonta|Metazoa|Eumetazoa|Triploblastica|Nephrozoa|Deuterostomia|Chordata|Vertebrata|Gnathostomata|Osteichthyes|Sarcopterygii|Dipnotetrapodomorpha|Tetrapodomorpha|Tetrapoda|Reptiliomorpha|Anthracosauria|Batrachosauria|Cotylosauria|Amniota|Sauropsida|Reptilia|Eureptilia|Romeriida|Diapsida|Archosauromorpha|Archosauriformes|Crurotarsi|Archosauria|Avemetatarsalia|Ornithodira|Dinosauromorpha|Dinosauriformes|Dinosauria|Saurischia|Theropoda|Neotheropoda|Averostra|Tetanurae|Avetheropoda|Coelurosauria|Maniraptora|Paraves|Aves|Charadriiformes|Limicolae|Scolopacides|Scolopacoidea|Scolopacidae|Totanus",
          "classificationRank": "unranked clade|unranked clade|subkingdom|unranked clade|unranked clade|unranked clade|unranked clade|unranked clade|unranked clade|unranked clade|unranked clade|superclass|subclass|subclass|unranked clade|unranked clade|unranked clade|unranked clade|unranked clade|unranked clade|unranked clade|class|unranked clade|unranked clade|unranked clade|infraclass|unranked clade|unranked clade|unranked clade|informal|unranked clade|unranked clade|unranked clade|unranked clade|unranked clade|unranked clade|unranked clade|unranked clade|unranked clade|unranked clade|suborder|unranked clade|unranked clade|class|order|suborder|infraorder|superfamily|family|genus",
          "classificationIDs": "288516|212579|2|85325|67102|85323|67145|33815|67149|67344|34881|67348|219195|77135|53190|125547|37177|99766|56749|53189|135358|36322|92204|99771|37768|38182|57091|66477|38215|144376|57250|53366|53207|52775|38505|38513|56397|92043|53374|55483|53940|55486|64113|36616|36640|98938|98941|98943|39581|39583",
          "matchType": "ExactCanonicalMatch"
        },
        "dataSourcesNum": 7,
        "dataSourceQuality": "HasCuratedSources",
        "retries": 1
      }
    }
  ]
}
